AUTHORS.rst
CONTRIBUTING.rst
HISTORY.rst
LICENSE
MANIFEST.in
README.rst
setup.cfg
setup.py
docs/Makefile
docs/authors.rst
docs/conf.py
docs/contributing.rst
docs/history.rst
docs/index.rst
docs/installation.rst
docs/make.bat
docs/readme.rst
docs/usage.rst
s3qlite/__init__.py
s3qlite/client.py
s3qlite/error_handlers.py
s3qlite/s3qlite.py
s3qlite/test.py
s3qlite.egg-info/PKG-INFO
s3qlite.egg-info/SOURCES.txt
s3qlite.egg-info/dependency_links.txt
s3qlite.egg-info/not-zip-safe
s3qlite.egg-info/top_level.txt
tests/__init__.py
tests/test_s3qlite.py