Metadata-Version: 1.1
Name: s3qlite
Version: 0.1.0
Summary: un queries across multiple sqlite files stored on s3 (or an s3-API-compliant-service)
Home-page: https://github.com/benmusch/s3qlite
Author: Ben Muschol
Author-email: benmuschol@gmail.com
License: MIT license
Keywords: s3qlite
Platform: UNKNOWN
Classifier: Development Status :: 2 - Pre-Alpha
Classifier: Intended Audience :: Developers
Classifier: License :: OSI Approved :: MIT License
Classifier: Natural Language :: English
Classifier: Programming Language :: Python :: 2
Classifier: Programming Language :: Python :: 2.6
Classifier: Programming Language :: Python :: 2.7
Classifier: Programming Language :: Python :: 3
Classifier: Programming Language :: Python :: 3.3
Classifier: Programming Language :: Python :: 3.4
Classifier: Programming Language :: Python :: 3.5
